ecal_calibration/calo_translator.py
ecal_calibration/corrector.py
ecal_calibration/network.py
ecal_calibration/preprocessor.py
ecal_calibration/regressor.py
ecal_calibration/utilities.py
ecal_calibration_data/brem_correction/coordinates.csv
ecal_calibration_data/brem_correction/mu_data_24c4MU_bybin_P_ELECTRONENERGY_region0.yaml
ecal_calibration_data/brem_correction/mu_data_24c4MU_bybin_P_ELECTRONENERGY_region1.yaml
ecal_calibration_data/brem_correction/mu_data_24c4MU_bybin_P_ELECTRONENERGY_region2.yaml
ecal_calibration_data/brem_correction/region0_bins.yaml
ecal_calibration_data/brem_correction/region1_bins.yaml
ecal_calibration_data/brem_correction/region2_bins.yaml
ecal_calibration_data/tests/corrector/simple.yaml
ecal_calibration_data/tests/preprocessor/simple.yaml
ecal_calibration_data/tests/regressor/row.json
ecal_calibration_data/tests/regressor/simple.yaml
ecal_calibration_scripts/make_toy_decays.py
ecal_calibration-1.7.3.dev8.dist-info/METADATA
ecal_calibration-1.7.3.dev8.dist-info/WHEEL
ecal_calibration-1.7.3.dev8.dist-info/entry_points.txt
ecal_calibration-1.7.3.dev8.dist-info/top_level.txt
ecal_calibration-1.7.3.dev8.dist-info/RECORD
