Metadata-Version: 2.4
Name: ecal_calibration
Version: 1.7.3.dev8
Summary: Project meant to apply offline corrections to electrons in LHCb
